update_conf.py-1.1.0.data/data/share/update-conf.py/update-conf.py.conf
update_conf_py/__init__.py
update_conf_py/main.py
update_conf.py-1.1.0.dist-info/LICENSE
update_conf.py-1.1.0.dist-info/METADATA
update_conf.py-1.1.0.dist-info/WHEEL
update_conf.py-1.1.0.dist-info/entry_points.txt
update_conf.py-1.1.0.dist-info/top_level.txt
update_conf.py-1.1.0.dist-info/RECORD
